CHANGES
LICENSE
MANIFEST.in
__init__.py
setup.py
test_session.py
Flask_Sessions.egg-info/PKG-INFO
Flask_Sessions.egg-info/SOURCES.txt
Flask_Sessions.egg-info/dependency_links.txt
Flask_Sessions.egg-info/not-zip-safe
Flask_Sessions.egg-info/requires.txt
Flask_Sessions.egg-info/top_level.txt
docs/Makefile
docs/__init__.py
docs/conf.py
docs/index.rst
docs/make.bat
docs/_static/flask-session.png
docs/_themes/.gitignore
docs/_themes/LICENSE
docs/_themes/README
docs/_themes/flask_theme_support.py
docs/_themes/flask/layout.html
docs/_themes/flask/relations.html
docs/_themes/flask/theme.conf
docs/_themes/flask/static/flasky.css_t
docs/_themes/flask_small/layout.html
docs/_themes/flask_small/theme.conf
docs/_themes/flask_small/static/flasky.css_t
flask_sessions/__init__.py
flask_sessions/sessions.py