Metadata-Version: 1.1
Name: Flask-Sessions
Version: 0.1.4
Summary: Adds server-side session support to your Flask application
Home-page: https://github.com/jefurry/flask-sessions
Author: Jefurry
Author-email: jefurry@qq.com
License: BSD
Platform: any
Classifier: Environment :: Web Environment
Classifier: Intended Audience :: Developers
Classifier: License :: OSI Approved :: BSD License
Classifier: Operating System :: OS Independent
Classifier: Programming Language :: Python
Classifier: Topic :: Internet :: WWW/HTTP :: Dynamic Content
Classifier: Topic :: Software Development :: Libraries :: Python Modules
